[
    {
        "title": "Accelerated Growth",
        "content": "Gain a competitive edge by leveraging our insights and resources."
    },
    {
        "title": "Reduced Risk",
        "content": "Mitigate the challenges of navigating the complex AI landscape."
    },
    {
        "title": "Increased Investment Potential",
        "content": "Enhance your startup's attractiveness to investors."
    },
    {
        "title": "Access to a Proven Network",
        "content": "Connect with industry leaders and potential partners."
    },
    {
        "title": "Continuous Learning",
        "content": "Stay updated on the latest AI trends and best practices."
    }
]